{"ver":"0.1","info":{"id":"4cKXzt","date":"1715626301","viewed":139,"name":"Circle Depth 3494879","username":"spenceryonce","description":"Fun little replication of an example processing program I found.  ","likes":1,"published":3,"flags":0,"usePreview":0,"tags":["circles","fun","depth","multiply"],"hasliked":0,"parentid":"","parentname":""},"renderpass":[{"inputs":[],"outputs":[{"id":"4dfGRr","channel":0}],"code":"#define res iResolution.xy\nvoid mainImage( out vec4 fragColor, in vec2 fragCoord )\n{\n    vec2 uv = (fragCoord - 0.5 * res) / res.y;\n    vec2 ouv = uv;\n    \n    vec3 col = vec3(0.0);\n    uv = fract(uv*30.0);\n    uv -= 0.5;\n    uv *= 2.7;\n    uv = vec3(length(uv)).rr;\n    \n    col = 1.0-uv.xyy;\n    col *= vec3(length(ouv));\n    \n    fragColor = vec4(col,1.0);\n}","name":"Image","description":"","type":"image"}]}