{"ver":"0.1","info":{"id":"7dfSD2","date":"1619241675","viewed":118,"name":"box_blur test","username":"Shellderr","description":"feedback applied box blur","likes":1,"published":1,"flags":32,"usePreview":0,"tags":["blur","convolution"],"hasliked":0,"parentid":"","parentname":""},"renderpass":[{"inputs":[{"id":"4dXGR8","filepath":"/media/previz/buffer00.png","previewfilepath":"/media/previz/buffer00.png","type":"buffer","channel":0,"sampler":{"filter":"linear","wrap":"clamp","vflip":"true","srgb":"false","internal":"byte"},"published":1}],"outputs":[{"id":"4dfGRr","channel":0}],"code":"void mainImage( out vec4 fragColor, in vec2 fragCoord )\n{\n    vec2 uv = fragCoord/iResolution.xy;\n    fragColor = texture(iChannel0, uv);\n}","name":"Image","description":"","type":"image"},{"inputs":[{"id":"4dfGRn","filepath":"/media/a/8de3a3924cb95bd0e95a443fff0326c869f9d4979cd1d5b6e94e2a01f5be53e9.jpg","previewfilepath":"/media/ap/8de3a3924cb95bd0e95a443fff0326c869f9d4979cd1d5b6e94e2a01f5be53e9.jpg","type":"texture","channel":0,"sampler":{"filter":"mipmap","wrap":"repeat","vflip":"true","srgb":"false","internal":"byte"},"published":1},{"id":"4dXGR8","filepath":"/media/previz/buffer00.png","previewfilepath":"/media/previz/buffer00.png","type":"buffer","channel":1,"sampler":{"filter":"linear","wrap":"clamp","vflip":"true","srgb":"false","internal":"byte"},"published":1}],"outputs":[{"id":"4dXGR8","channel":0}],"code":"#define a .004\n\nvoid mainImage( out vec4 fragColor, in vec2 fragCoord ){\n\n    vec2 uv = fragCoord.xy/iResolution.xy;\n    vec4 tc = iFrame < 7 ? texture(iChannel0, uv) : mix( texture(iChannel0, uv), texture(iChannel1, uv), .99);\n    \n    tc += texture(iChannel1, uv+vec2(-a,-a))*.5;\n    tc += texture(iChannel1, uv+vec2(0.,-a))*.5;\n    tc += texture(iChannel1, uv+vec2(a, -a))*.5;\n    \n    tc += texture(iChannel1, uv+vec2(-a,0.))*.5;\n   // tc += texture(iChannel0, uv+vec2(0.,0.))*.5;\n    tc += texture(iChannel1, uv+vec2(a, 0.))*.5;\n    \n    tc += texture(iChannel1, uv+vec2(-a, a))*.5;\n    tc += texture(iChannel1, uv+vec2(0., a))*.5;\n    tc += texture(iChannel1, uv+vec2(a,  a))*.5;\n\n    tc *= .2;\n    \n    fragColor = tc;\n    \n}","name":"Buffer A","description":"","type":"buffer"}]}