{"ver":"0.1","info":{"id":"7sdBWH","date":"1656480552","viewed":61,"name":"buratinoo ","username":"Slanka","description":"day 2","likes":0,"published":1,"flags":0,"usePreview":0,"tags":["practice"],"hasliked":0,"parentid":"","parentname":""},"renderpass":[{"inputs":[],"outputs":[{"id":"4dfGRr","channel":0}],"code":"    bool circle(vec2 uv, vec2 center, float r)\n    {\n      return (uv.x + center.x) * (uv.x + center.x) + (uv.y + center.y) * (uv.y + center.y) < r*r; \n    }\n    bool lineOver(vec2 uv, vec3 line) \n    {\n      return uv.y * line.y >= uv.x * line.x + line.z;\n    }\n    bool lineUnder(vec2 uv, vec3 line) \n    {\n      return uv.y * line.y <= uv.x * line.x + line.z;\n    }\n\n\nvoid mainImage(out vec4 fragColor, in vec2 fragCoord)\n{\n    // Normalized pixel coordinates (from 0 to 1)\n    vec2 uv =2.0*fragCoord/iResolution.xy-1.0 ;\n     uv.x = uv.x*iResolution.x/iResolution.y;\n    \n    \n    fragColor = vec4(1.0, 1.0, 1.0, 1.0);\n    \n    //головa\n      if(circle(uv, vec2(0.7, 0.2), 0.35))\n         fragColor = vec4(1.0, 0.8, 0.8, 1.0);    \n      if(circle(uv, vec2(0.6, 0.08), 0.08))\n         fragColor = vec4(0, 0, 0, 1.0);      \n      if(circle(uv, vec2(0.6, 0.05), 0.085))\n         fragColor = vec4(1.0, 0.8, 0.8, 1.0);\n      \n      //находится ли точка сверху или снизу от заданной прямой \n      if(lineOver(uv, vec3(1.0, -14.0, 1.97)) && lineUnder(uv, vec3(-1.0, -14.0, 3.0)) && uv.x >= -0.36) \n         fragColor = vec4(1.0, 0.8, 0.8, 1.0);\n      \n      if(circle(uv, vec2(0.54, 0.41), 0.080))\n         fragColor = vec4(0, 0, 0, 1.0);\n      if(circle(uv, vec2(0.56, 0.43), 0.083))\n         fragColor = vec4(1.0, 0.8, 0.8, 1.0);     \n      if(circle(uv, vec2(0.75, 0.28), 0.11))\n         fragColor = vec4(1, 0.4, 0.5, 1.0);\n        \n        //шляпа \n      if(uv.y >= 0.14 && uv.y <= 0.23 && uv.x >= -0.97 && uv.x <= -0.43)\n         fragColor = vec4(1, 0.6, 0.9, 1.0);   \n      if(circle(uv, vec2(0.4, -0.18), 0.06))\n         fragColor = vec4(1, 0.6, 0.9, 1.0);       \n      if(circle(uv, vec2(0.95, -0.18), 0.06))\n         fragColor = vec4(1, 0.6, 0.9, 1.0);      \n      if(uv.y >= 0.17 && uv.y <= 0.23 && uv.x >= -0.97 && uv.x <= -0.4)\n         fragColor = vec4(1, 0.6, 0.9, 1.0);    \n      if(circle(uv, vec2(0.41, -0.18), 0.045)) \n         fragColor = vec4(1, 0.7, 0.3, 1.0);      \n      if(circle(uv, vec2(0.94, -0.18), 0.045)) \n         fragColor = vec4(1, 0.7, 0.3, 1.0);    \n      if(lineOver(uv, vec3(-3., -1.0, -3)) && lineUnder(uv, vec3(-3.0, 1.0, -1)) && uv.y >= 0.23 && uv.y <= 0.9) \n         fragColor = vec4(1, 0.6, 0.9, 1.0);     \n      if(circle(uv, vec2(0.67, -0.87), 0.10)) \n         fragColor = vec4(1, 0.7, 0.3, 1.0);\n      \n      //тело      \n      if(circle(uv, vec2(0.7, 0.987), 0.445)) \n         fragColor = vec4(1, 0.6, 0.9, 1.0);       \n      if(circle(uv, vec2(0.38, 0.95), 0.05)) \n         fragColor = vec4(1, 1, 0.7, 1.0);         \n      if(circle(uv, vec2(0.45, 0.79), 0.05)) \n         fragColor = vec4(1, 1, 0.7, 1.0);        \n      if(circle(uv, vec2(0.55, 0.65), 0.05)) \n         fragColor = vec4(1, 1, 0.7, 1.0);\n}","name":"Image","description":"","type":"image"}]}