{"ver":"0.1","info":{"id":"7slfWN","date":"1644904228","viewed":135,"name":"Fancy Sine Wallpaper","username":"trigophers","description":"I was just messing around","likes":8,"published":1,"flags":0,"usePreview":0,"tags":["sine","fancy","wallpaper","isf"],"hasliked":0,"parentid":"","parentname":""},"renderpass":[{"inputs":[],"outputs":[{"id":"4dfGRr","channel":0}],"code":"vec2 f(vec2 x, float t) {\n    return vec2(cos(x.x+sin(t*3.0))+x.y+sin(t*2.)/2.0+0.5, sin(x.y+t+6.28*iMouse.x/iResolution.x+sin(t*5.))+x.x);\n}\n\nvoid mainImage( out vec4 fragColor, in vec2 fragCoord )\n{\n    vec2 uv = (fragCoord-iResolution.xy/2.0)/iResolution.y*30.+vec2(50, 0);\n    vec2 x = uv;\n    for(int i = 0; i < 20; i++) {\n        x = f(x, iTime/5.0);\n    }\n    float t = length(x)/100.0;\n    fragColor = vec4(pow(vec3(t), vec3(0.4545, 0.6545, 0.8545*(1.-iMouse.y/iResolution.y))), 1.0);\n}\n","name":"Image","description":"","type":"image"}]}