{"ver":"0.1","info":{"id":"clBGzV","date":"1673523345","viewed":54,"name":"LODFade","username":"jiangyiheng","description":"LODFade ","likes":0,"published":1,"flags":0,"usePreview":0,"tags":["lodfade"],"hasliked":0,"parentid":"","parentname":""},"renderpass":[{"inputs":[],"outputs":[{"id":"4dfGRr","channel":0}],"code":"float bayer4x4(uvec2 ip) {\n    uint x = ip.x, y = ip.y;\n    uint t = x^y;\n    return float(((t<<3)&8u)|((y<<2)&4u)|(t&2u)|((y>>1)&1u) + 1u) / 18.0;\n}\n\nbool fade (float progress, float thres) {\n    if (progress > 0.5) thres = 1.0 - thres;\n    return progress > thres;\n}\n\nvoid mainImage( out vec4 fragColor, in vec2 fragCoord )\n{\n    // default color\n    fragColor = vec4(0,0,0,0);\n    float progress = 0.5 * (sin(fract(iTime * 0.05)*2.0*3.14159265) + 1.0);\n    uvec2 ip = uvec2(fragCoord.xy);\n    \n    float thres = bayer4x4(ip);\n\n    \n    if (fade(progress, thres)) \n        fragColor = vec4(1,0,0,0);\n        \n    if (fade(1.0 - progress, thres)) \n        fragColor = vec4(0,1,0,0);\n}","name":"Image","description":"","type":"image"}]}