{"ver":"0.1","info":{"id":"DdKSWR","date":"1681291370","viewed":86,"name":"FirstStudyShader","username":"ITSanta","description":"MyFirstStudyShader","likes":0,"published":1,"flags":0,"usePreview":0,"tags":["2d"],"hasliked":0,"parentid":"","parentname":""},"renderpass":[{"inputs":[],"outputs":[{"id":"4dfGRr","channel":0}],"code":"vec4 black = vec4(1.0,1.0,1.0,1.0);\nfloat level = 10.0;\n\n// Gamma correction\nvoid gammaCorrection( inout vec4 fragColor )\n{\n    fragColor = pow(fragColor, vec4(1./2.2));\n}\n\nvoid stepGrayColor( inout vec4 fragColor, in vec2 fragCoord )\n{\n    float x = fragCoord.x / iResolution.x;\n    x = float(int(x * 10.0)) / 10.0;\n    fragColor = black * x;\n}\n\nvoid stepGrayColorWithGamma( inout vec4 fragColor, in vec2 fragCoord )\n{\n    stepGrayColor(fragColor, fragCoord);\n    gammaCorrection(fragColor);\n}\n\n\nvoid mainImage( out vec4 fragColor, in vec2 fragCoord )\n{\n    \n    //stepGrayColor(fragColor, fragCoord);\n    //[0,25, 51, 76,102,127,153,178,204,229]\n    \n    stepGrayColorWithGamma(fragColor, fragCoord);\n    //[0,90,123,147,168,186,202,217,230,243]\n\n}\n\n","name":"Image","description":"","type":"image"}]}