{"ver":"0.1","info":{"id":"DdKXDy","date":"1681555213","viewed":106,"name":"Fresnel 2d effect","username":"vladosina","description":"Fresnel Effect","likes":2,"published":1,"flags":0,"usePreview":0,"tags":["fresnel"],"hasliked":0,"parentid":"","parentname":""},"renderpass":[{"inputs":[],"outputs":[{"id":"4dfGRr","channel":0}],"code":"const float scale = 3.;\nconst float power = 0.7;\n\nfloat fresnel(vec2 uv, float scale, float power) {\n    return 1. - pow(1. - length(uv * scale), power);\n}\n\nvoid mainImage( out vec4 fragColor, in vec2 fragCoord ) {\n    vec2 uv = (fragCoord - 0.5 * iResolution.xy) / iResolution.y;\n\n    fragColor = vec4(vec3(fresnel(uv, scale, power)),1.0);\n}","name":"Image","description":"","type":"image"}]}