{"ver":"0.1","info":{"id":"DsSczh","date":"1687385281","viewed":149,"name":"Random Rectangle Noise","username":"Markant","description":"Random Rectangle Noise","likes":4,"published":3,"flags":0,"usePreview":0,"tags":["noise"],"hasliked":0,"parentid":"","parentname":""},"renderpass":[{"inputs":[],"outputs":[{"id":"4dfGRr","channel":0}],"code":"void mainImage(out vec4 fragColor, in vec2 fragCoord)\n{\n    vec2 rectSize = iResolution.xy / 10.0;\n    vec2 rectCoord = floor(fragCoord / rectSize);\n    \n    float randomValue = fract(sin(dot(rectCoord, vec2(11.5621, 78.943))) * (iTime/10000.) * 4358.5453);\n    \n    fragColor = randomValue < 0.3 ? vec4(1.) : vec4(0.);\n}\n","name":"Image","description":"","type":"image"}]}