{"ver":"0.1","info":{"id":"flsGWf","date":"1623006612","viewed":1194,"name":"OpenSetTest8","username":"OpenSet","description":"Click and drag on the window to change effect","likes":20,"published":3,"flags":38,"usePreview":1,"tags":["webcam"],"hasliked":0,"parentid":"","parentname":""},"renderpass":[{"inputs":[{"id":"XdXGRr","filepath":"/presets/mic.png","previewfilepath":"/presets/mic.png","type":"mic","channel":1,"sampler":{"filter":"linear","wrap":"clamp","vflip":"true","srgb":"false","internal":"byte"},"published":1},{"id":"4dXGR8","filepath":"/media/previz/buffer00.png","previewfilepath":"/media/previz/buffer00.png","type":"buffer","channel":0,"sampler":{"filter":"linear","wrap":"clamp","vflip":"true","srgb":"false","internal":"byte"},"published":1}],"outputs":[{"id":"4dfGRr","channel":0}],"code":"void mainImage( out vec4 fragColor, in vec2 fragCoord )\n{\n\tvec2 uv = fragCoord.xy / iResolution.xy;\n\tvec4 c = texture(iChannel0, uv);\n    c.rgb = sin(c.rgb*(30.0+iMouse.y*80.0/iResolution.y)+iTime+vec3(50., 0.2,.5*texture(iChannel1, vec2(1.5*length(uv-.4),10.)).r))*.45+.5;\n    fragColor = c;\n}","name":"Image","description":"","type":"image"},{"inputs":[{"id":"4sf3zn","filepath":"/presets/webcam.png","previewfilepath":"/presets/webcam.png","type":"webcam","channel":1,"sampler":{"filter":"linear","wrap":"clamp","vflip":"true","srgb":"false","internal":"byte"},"published":1},{"id":"4sf3zn","filepath":"/presets/webcam.png","previewfilepath":"/presets/webcam.png","type":"webcam","channel":3,"sampler":{"filter":"linear","wrap":"clamp","vflip":"true","srgb":"false","internal":"byte"},"published":1},{"id":"XdXGRr","filepath":"/presets/mic.png","previewfilepath":"/presets/mic.png","type":"mic","channel":2,"sampler":{"filter":"linear","wrap":"clamp","vflip":"true","srgb":"false","internal":"byte"},"published":1},{"id":"4dXGR8","filepath":"/media/previz/buffer00.png","previewfilepath":"/media/previz/buffer00.png","type":"buffer","channel":0,"sampler":{"filter":"linear","wrap":"clamp","vflip":"true","srgb":"false","internal":"byte"},"published":1}],"outputs":[{"id":"4dXGR8","channel":0}],"code":"void mainImage( out vec4 fragColor, in vec2 fragCoord )\n{\n    vec2 uv = fragCoord.xy / iResolution.xy;\n    float z = (texture(iChannel2, vec2(length(uv-.5),1.)).r)*(20.0/iResolution.x*0.2+.001);\n    float zoom = (1.-z);sin(iTime*20.)*.51+.9;\n    uv-=.5;\n    uv*=zoom;\n    uv+=.5;\n    vec4 o = texture(iChannel0, uv);\n    vec4 c = texture(iChannel3,uv);\n    c = mix(c,o,.95);\n    fragColor = c;\n}","name":"Buffer A","description":"","type":"buffer"}]}