{"ver":"0.1","info":{"id":"flyGzt","date":"1638133193","viewed":92,"name":"Wavy Blue Thingy Thing","username":"Dayshadow_","description":"Looks interesting I guess\n","likes":0,"published":1,"flags":0,"usePreview":0,"tags":["wocky"],"hasliked":0,"parentid":"","parentname":""},"renderpass":[{"inputs":[],"outputs":[{"id":"4dfGRr","channel":0}],"code":"\nvec2 rotateUV(vec2 uv, float rotation)\n{\n    float mid = 0.5;\n    return vec2(\n        cos(rotation) * (uv.x - mid) + sin(rotation) * (uv.y - mid) + mid,\n        cos(rotation) * (uv.y - mid) - sin(rotation) * (uv.x - mid) + mid\n    );\n}\n\n\nvoid mainImage( out vec4 fragColor, in vec2 fragCoord )\n{\n    // Normalized pixel coordinates (from 0 to 1)\n    vec2 uv = fragCoord/iResolution.xy;\n    \n    vec2 uvd = rotateUV(uv, 1.0) + (sin(uv.x*17.0 + iTime/1.0) / (8.0 + (uv.x * iTime)/80.0));\n\n    \n    float waveStrength = abs(cos(uvd.x * 20.0 + iTime)) + fract(sin((uvd.x + uv.x) * 10.0));\n    \n    float highlight = 1.0 - smoothstep(0.0, 0.5, waveStrength);\n    \n    vec3 highlightCol = vec3(uvd, uv.x);\n\n    vec3 col = vec3(0.011, 0.098, 0.866) * waveStrength + highlightCol * highlight;\n\n    // Output to screen\n    fragColor = vec4(col,1.0);\n}\n\n","name":"Image","description":"","type":"image"}]}