{"ver":"0.1","info":{"id":"llKXzV","date":"1485138085","viewed":121,"name":"Checkerboard Shader","username":"kevpegan","description":"Creates a checkerboard with changeable colors and columns / rows. ","likes":0,"published":1,"flags":0,"usePreview":0,"tags":["2d"],"hasliked":0,"parentid":"","parentname":""},"renderpass":[{"inputs":[],"outputs":[{"id":"4dfGRr","channel":0}],"code":"void mainImage( out vec4 fragColor, in vec2 fragCoord )\n{\n    //variable that decides the number of columns and rows\n    float numColumnsAndRows = 10.0;\n    \n    //assigns the primary and secondary colors\n    vec4 firstColor = vec4(1.0, 1.0, 1.0, 1.0);\n    vec4 secondColor = vec4(0.0, 0.0, 0.0, 1.0);\n    \n\tvec2 uv = fragCoord.xy / iResolution.xy;\n    \n    float xDir = uv.x;\n    float yDir = uv.y;\n    \n\t//use floor to get which column or row the pixel is in, and then use mod to check if it is even or odd\n    float fmodResult = mod(floor(numColumnsAndRows * xDir) + floor(numColumnsAndRows * yDir), 2.0);\n\t\n    //if odd, primary color. if even, secondary color\n    if (fmodResult < 1.0)\n    {\n      fragColor = firstColor;\n    } \n    else \n    {\n      fragColor = secondColor;\n    }\n}","name":"Image","description":"","type":"image"}]}