{"ver":"0.1","info":{"id":"lttXDf","date":"1481987755","viewed":479,"name":"Microphone Basics","username":"ptrgags","description":"Thanks to this shader by iq (https://www.shadertoy.com/view/Xds3Rr) I learned how easy it is to work with audio textures.\n\n\nThis is a quick little test to visualize the audio that goes into the microphone.","likes":2,"published":1,"flags":4,"usePreview":0,"tags":["2d","visualization","basics","microphone","audo"],"hasliked":0,"parentid":"","parentname":""},"renderpass":[{"inputs":[{"id":"XdXGRr","filepath":"/presets/mic.png","previewfilepath":"/presets/mic.png","type":"mic","channel":0,"sampler":{"filter":"linear","wrap":"clamp","vflip":"true","srgb":"false","internal":"byte"},"published":1}],"outputs":[{"id":"4dfGRr","channel":0}],"code":"void mainImage( out vec4 fragColor, in vec2 fragCoord )\n{\n\tvec2 uv = fragCoord.xy / iResolution.xy;\n    if (uv.y > 0.5) {\n        //First row shows FFT analysis (amplitude as a function of frequency)\n        vec4 orange = vec4(1.0, 0.5, 0.0, 1.0);\n\t\tfragColor = texture(iChannel0, vec2(uv.x, 0.25)).x * orange;\n    } else {\n        //Second row shows waveform (amplitude as a function of time)\n        vec4 purple = vec4(0.5, 0.0, 1.0, 1.0);\n        fragColor = texture(iChannel0, vec2(uv.x, 0.75)) * purple;\n    }\n}","name":"Image","description":"","type":"image"}]}