{"ver":"0.1","renderpass":[{"outputs":[],"inputs":[{"channel":0,"type":"texture","id":"4dfGRn","filepath":"/media/a/8de3a3924cb95bd0e95a443fff0326c869f9d4979cd1d5b6e94e2a01f5be53e9.jpg","sampler":{"filter":"mipmap","wrap":"repeat","vflip":"false","srgb":"false","internal":"byte"}}],"code":"const vec2 MED = vec2(0.5,0.5);\n\nvoid mainImage( out vec4 fragColor, in vec2 fragCoord )\n{\n\tvec2 uv = fragCoord.xy / iResolution.xy;\n    vec2 p = uv - MED;\n    float a = iTime; //1.570796326;//iTime; //0.35;\n    float c = cos(a);\n    float s = sin(a);\n    vec2 fUV = vec2( p.x*c - p.y*s, p.x*s + p.y*c );\n    vec4 cor = texture(iChannel0,MED+fUV);\n\tfragColor = cor + vec4(0.0,0.0,0.0,0.0); //vec4(uv,0.5+0.5*sin(iTime),1.0);\n}","name":"Image","description":"","type":"image"}],"flags":{"mFlagVR":false,"mFlagWebcam":false,"mFlagSoundInput":false,"mFlagSoundOutput":false,"mFlagKeyboard":false,"mFlagMultipass":false,"mFlagMusicStream":false},"info":{"id":"MdjSD1","date":"1411741143","viewed":234,"name":"Simple UV rotator","username":"marcosbitetti","description":"Simple rotation to UV","likes":4,"published":1,"flags":0,"usePreview":0,"tags":["texture","rotation"],"hasliked":0,"parentid":"","parentname":""}}