{"ver":"0.1","info":{"id":"MdSczW","date":"1661348597","viewed":120,"name":"old school tunnel","username":"jent","description":"sample texture with polar coords","likes":3,"published":1,"flags":0,"usePreview":0,"tags":["texturesampling"],"hasliked":0,"parentid":"","parentname":""},"renderpass":[{"inputs":[{"id":"XsXGRn","filepath":"/media/a/cd4c518bc6ef165c39d4405b347b51ba40f8d7a065ab0e8d2e4f422cbc1e8a43.jpg","previewfilepath":"/media/ap/cd4c518bc6ef165c39d4405b347b51ba40f8d7a065ab0e8d2e4f422cbc1e8a43.jpg","type":"texture","channel":0,"sampler":{"filter":"mipmap","wrap":"repeat","vflip":"true","srgb":"false","internal":"byte"},"published":1}],"outputs":[{"id":"4dfGRr","channel":0}],"code":"#define TWOPI 6.28318530718\n\nvec3 tunnel(sampler2D sampler, in vec2 uv, in float time) {\n    float r = length(uv);\n    float a = time + atan(uv.y,uv.x);\n    float b = time + atan(uv.y,abs(uv.x));\n    \n    vec2 uvL = vec2(1.0/r + time, a/3.1415927);\n    vec2 uvR = vec2(1.0/r + time, b/3.1415927);\n    \n\treturn textureGrad(sampler, uvL, dFdx(uvR), dFdy(uvR)).xyz;\n}\n\n\nvoid mainImage( out vec4 fragColor, in vec2 fragCoord )\n{\n\tvec2 uv = (2.*fragCoord - iResolution.xy) / iResolution.y;\n    float t = 0.01 * iTime;\n    fragColor = vec4(tunnel(iChannel0, uv, t), 0.0) * length(uv);\n\n}","name":"Image","description":"","type":"image"}]}