{"ver":"0.1","info":{"id":"MlfBW7","date":"1512055430","viewed":78,"name":"First_Homework","username":"vincentsk","description":"Circle in rectangle separated to two fields in different colors.","likes":0,"published":1,"flags":0,"usePreview":0,"tags":["homework","razvan"],"hasliked":0,"parentid":"","parentname":""},"renderpass":[{"inputs":[],"outputs":[{"id":"4dfGRr","channel":0}],"code":"void mainImage( out vec4 fragColor, in vec2 fragCoord )\n{\n\n    vec2 start_point = vec2(0.0, 0.0);\n    vec2 center_point = iResolution.xy / 2.0;\n    float circle_radius = center_point.y * 0.8 ; \n    \n    float greenColor = step(distance(center_point, fragCoord), circle_radius);\n    float blueColor = max(step(center_point.x, fragCoord.x) - greenColor, 0.0);\n    float redColor = 1.0 - blueColor - greenColor;\n    \n    fragColor = vec4(redColor, greenColor, blueColor,1.0);\n}","name":"Image","description":"","type":"image"}]}