{"ver":"0.1","info":{"id":"msf3z7","date":"1665846738","viewed":147,"name":"Artober - Acid","username":"Flopine","description":"Day 15 of the artober challenge : a quick doodle with hexagonal grid and lines","likes":14,"published":1,"flags":0,"usePreview":1,"tags":["2d","hexagon","rainbow","pattern","everyday"],"hasliked":0,"parentid":"","parentname":""},"renderpass":[{"inputs":[{"id":"4dXGzn","filepath":"/media/a/0c7bf5fe9462d5bffbd11126e82908e39be3ce56220d900f633d58fb432e56f5.png","previewfilepath":"/media/ap/0c7bf5fe9462d5bffbd11126e82908e39be3ce56220d900f633d58fb432e56f5.png","type":"texture","channel":0,"sampler":{"filter":"mipmap","wrap":"repeat","vflip":"true","srgb":"false","internal":"byte"},"published":1}],"outputs":[{"id":"4dfGRr","channel":0}],"code":"// Code by Flopine\n\n// Thanks to wsmind, leon, XT95, lsdlive, lamogui, \n// Coyhot, Alkama,YX, NuSan, slerpy, wwrighter \n// BigWings, FabriceNeyret and Blackle for teaching me\n\n// Thanks LJ for giving me the spark :3\n\n// Thanks to the Cookie Collective, which build a cozy and safe environment for me \n// and other to sprout :)  \n// https://twitter.com/CookieDemoparty\n\n\n#define PI acos(-1.)\n#define TAU (2.*PI)\n#define hr vec2(1.,sqrt(3.))\n\n#define rot(a) mat2(cos(a),sin(a),-sin(a),cos(a))\n\n#define hd(u, s) (max(abs(u.x), dot(abs(u), normalize(hr)))-s)\n#define circle(u,s) (length(u)-s)\n#define AAstep(thre, val) smoothstep(-.7,.7,(val-thre)/min(0.02,fwidth(val-thre)))\n\n#define palette(t,c,d) (vec3(0.5)+vec3(0.5)*cos(TAU*(c*t+d)) )\n\n#define noise(u) textureLod(iChannel0, u, 0.).x\n\n\nfloat moda(inout vec2 p, float rep)\n{\n    float per = TAU/rep;\n    float a = atan(p.y,p.x);\n    float c = floor(a/per);\n    a = mod(a,per)-per*.5;\n    if (abs(c) >= (rep*.5)) c = abs(c);\n    p = vec2(cos(a), sin(a))*length(p);\n    return c;\n}\n\nvec4 hexgrid (vec2 uv)\n{\n    vec2 ga=mod(uv,hr)-hr*.5, gb=mod(uv-hr*.5,hr)-hr*.5, \n    guv=dot(ga,ga)<dot(gb,gb)?ga:gb, gid=uv-guv;\n    return vec4(guv,gid);\n}\n\nvec3 frame (vec2 uv)\n{\n    vec4 hg = hexgrid(uv);\n    vec2 uu = hg.xy, uid = hg.zw;    \n    float uswi = noise(uid*.25);\n    \n    float h = 1.;\n    \n    float aid = moda(uu, 6.);  \n    h *= AAstep(0.001, abs(uu.y)-0.01);\n    \n    if (uswi <.5)\n    {\n        uu.x -= 0.5;\n        h *= AAstep( 0.02, abs(circle(uu, 0.25)) );\n    }\n\n    h *= AAstep( 0.02, abs(circle(uu, 0.35)) ); \n    uu.x -= 0.435;\n    h *= AAstep(0.001, abs(uu.x)-0.01);\n    \n    return mix(palette(aid+mod(uid.x*uid.y, 2.), vec3(.1), vec3(0.3,0.8,0.1)), vec3(0.),  h);\n}\n\nvoid mainImage( out vec4 fragColor, in vec2 fragCoord )\n{\n    vec2 uv = (2.*fragCoord-iResolution.xy)/iResolution.y;\n    \n    uv.y += iTime*.3;\n    uv *= 2.;\n    \n    vec3 col = frame(uv);\n\n    fragColor = vec4(sqrt(col),1.0);\n}","name":"Image","description":"","type":"image"}]}