{"ver":"0.1","info":{"id":"mtfyzM","date":"1690512780","viewed":35,"name":"July 27, 2023","username":"HTR1997","description":"close","likes":0,"published":1,"flags":0,"usePreview":0,"tags":["moon"],"hasliked":0,"parentid":"","parentname":""},"renderpass":[{"inputs":[],"outputs":[{"id":"4dfGRr","channel":0}],"code":"void mainImage( out vec4 fragColor, in vec2 fragCoord )\n{\n\n    vec2 uv = fragCoord/iResolution.xy;\n    vec2 ab = (fragCoord * 2.0 - iResolution.xy)/iResolution.y;\n\n    // Time varying pixel color\n    vec3 col = vec3(0.,0.,0.);\n    col += .0;\n    \n    \n    vec2 pt = vec2(0., 0.);\n    pt.x += cos(4.*iTime);\n    pt.y += sin(4.*iTime);\n    //col.rg += 0.1/length(ab - pt);\n    \n    \n    //col.b += .01/length(ab.x-pt.x/2.);\n    //col.r += .01/length(ab.y-pt.x);\n    \n    col += 0.03/(1.-\n            ( step(1.,\n                //length(2.+2.*cos(mod(iTime,3.1415))+ab) ) * step(0.,1.-length(ab)))\n                length(1.5*cos(iTime)+ab))* step(0.,1.-length(ab)))\n            );\n    \n    \n    // Output to screen\n    fragColor = vec4(col,1.0);\n}","name":"Image","description":"","type":"image"}]}