{"ver":"0.1","info":{"id":"MXf3Rf","date":"1707766154","viewed":62,"name":"Galaxy travelling","username":"Gfscalco","description":"A simple 3 layers of circles to simulate a high speed movement in space. \nPracticing what i learned from the \"Generative designs\" chapter from the book of shaders.","likes":5,"published":1,"flags":0,"usePreview":0,"tags":["random","galaxy","stars","learning","tile","tiles"],"hasliked":0,"parentid":"","parentname":""},"renderpass":[{"inputs":[],"outputs":[{"id":"4dfGRr","channel":0}],"code":"// Author @gfscalco - 2024\n// A truchet tile composed of rotated 1/4 circles\n\n\n#define PI 3.14159265358979323846\n\nfloat random (in vec2 _st) {\n    return fract(sin(dot(_st.xy,\n                         vec2(12.9898,78.233)))*\n        43758.5453123);\n}\n\nvec2 random_vec2(in vec2 _st){\n    return fract(sin(_st.xy)*43758.5453123);\n}\n\nfloat circle(in vec2 pixel, in float r)\n{\n    vec2 pos = vec2(0.5);\n    pixel = pixel - pos;\n    float angle = atan(pixel.y/pixel.x);\n    float radius = length(pixel);\n    float mask = smoothstep(r-0.005,r+0.35, radius);\n    return (1.0-mask);\n}\n\n\nvoid mainImage( out vec4 fragColor, in vec2 fragCoord )\n{\n    vec2 st = fragCoord.xy/iResolution.xy;\n\n    //Creating the moving systems\n    vec2 moving_st_1 = st;\n    moving_st_1.x += 10.0*iTime*0.1;    \n    \n    vec2 moving_st_2 = st;\n    moving_st_2.x += 7.0*iTime*0.1;\n    \n    vec2 moving_st_3 = st;\n    moving_st_3.x += 5.0*iTime*0.1;\n    \n    \n    //Further layer coordiante system    \n    vec2 st_layer1 = moving_st_1;\n    st_layer1 *= 25.0;\n    vec2 ipos1 =  floor(st_layer1);    \n    float dots_1_speed = iTime*(random(ipos1));\n    vec2 fpos1 = fract(st_layer1); \n    //Medium layer coordiante system\n    vec2 st_layer2 = moving_st_2;\n    st_layer2 *= 15.0;\n    vec2 ipos2 =  floor(st_layer2);\n    vec2 fpos2 = fract(st_layer2);\n    //Closest layer coordinate system\n    vec2 st_layer3 = moving_st_3;\n    st_layer3 *= 5.0;\n    vec2 ipos3 =  floor(st_layer3);\n    vec2 fpos3 = fract(st_layer3);\n    \n    \n    //\"stars\" in the further layer    \n    float dots_1 = step(0.80,circle(vec2(fpos1.x + 1.0*random_vec2(ipos1).y-0.5, fpos1.y + 1.0*random_vec2(ipos1).x-0.5 ),0.02)*(random(ipos1)));\n\n    //\"stars\" in the medium layer\n    float dots_2 = step(0.85,circle(vec2(fpos2.x + 0.8*random_vec2(ipos2).y-0.4, fpos2.y + 0.8*random_vec2(ipos2).x-0.4 ),0.03)*(random(ipos2)));\n    \n    //\"stars\" in the closes layer\n    float dots_3 = step(0.90,circle(vec2(fpos3.x + 0.7*random_vec2(ipos3).y-0.35, fpos3.y + 0.7*random_vec2(ipos3).x-0.35),0.04)*(random(ipos3)));\n    \n\n    fragColor = vec4(vec3(dots_1 + dots_2 + dots_3),1.0);\n}\n\n","name":"Image","description":"","type":"image"}]}