{"ver":"0.1","info":{"id":"slyGR3","date":"1638137790","viewed":115,"name":"Center Spiral.SV","username":"turtlelover891","description":"a fun little challenge that I decided to take on","likes":5,"published":1,"flags":0,"usePreview":0,"tags":["spiral"],"hasliked":0,"parentid":"","parentname":""},"renderpass":[{"inputs":[],"outputs":[{"id":"4dfGRr","channel":0}],"code":"const float pi = acos(-1.);\n\nfloat atan2(float y, float x){\n    if(x >= 0.){\n        return atan(y/x)/pi/2.+.75;\n    }\n    return (pi+2.*atan(y/x))/4./pi;\n}\n\nvoid mainImage( out vec4 fragColor, in vec2 fragCoord )\n{\n    //======================\n    //parameters\n    int amount = 1;\n    float width = 5.;\n    float speed = 1.;\n    vec3 color1 = vec3(1.0, 1.5, 1.0);\n    vec3 color2 = vec3(-0.1, 0.0, 0.1);\n    //======================\n\n    vec2 R = iResolution.xy;\n    vec2 uv = fragCoord-R/2.;\n    vec3 col;\n    float circle = sqrt(uv.x*uv.x+uv.y*uv.y);\n    float d = (circle/100.);\n    d -= iTime*speed;\n\n    float mask = smoothstep(R.y/2.+width*4., R.y/2.-width*4., circle);\n    \n    col = vec3(sin((2.*pi*atan2(uv.y, uv.x)+d*width)*float(amount))+1.)/2.;\n    col = color1+col*(color2-color1);\n    col *= mask;\n    fragColor = vec4(col,1.0);\n}","name":"Image","description":"","type":"image"}]}