{"ver":"0.1","info":{"id":"WdtSDs","date":"1573249955","viewed":71,"name":"interferention","username":"Virg","description":"aaaaaaaa","likes":2,"published":1,"flags":0,"usePreview":0,"tags":["light"],"hasliked":0,"parentid":"","parentname":""},"renderpass":[{"inputs":[],"outputs":[{"id":"4dfGRr","channel":0}],"code":"void mainImage( out vec4 fragColor, in vec2 fragCoord )\n{\n    vec2 centerA = iResolution.xy/2.;\n    vec2 centerB = centerA;\n    centerA.x-=150.;\n    centerB.x+=150.;\n    float brightness=0.01;\n    float deBrightA=pow(distance(fragCoord,centerA)*brightness,2.);\n    float deBrightB=pow(distance(fragCoord,centerB)*brightness,2.);\n    float brightA=sin(distance(fragCoord,centerA)/4.-iTime);\n    float brightB=sin(distance(fragCoord,centerB)/4.-iTime);\n    float pxVal = brightA/deBrightA+brightB/deBrightB;\n    vec3 col = vec3(1.*pxVal);\n    fragColor = vec4(col,1.0);\n}","name":"Image","description":"","type":"image"}]}