{"ver":"0.1","info":{"id":"WlG3Wc","date":"1580006713","viewed":136,"name":"coral sea","username":"jiaolyulu1","description":"inspired by the mysterious mountain by Dave Hoskin","likes":5,"published":1,"flags":0,"usePreview":0,"tags":["2d"],"hasliked":0,"parentid":"","parentname":""},"renderpass":[{"inputs":[{"id":"XdfGRn","filepath":"/media/a/e6e5631ce1237ae4c05b3563eda686400a401df4548d0f9fad40ecac1659c46c.jpg","previewfilepath":"/media/ap/e6e5631ce1237ae4c05b3563eda686400a401df4548d0f9fad40ecac1659c46c.jpg","type":"texture","channel":0,"sampler":{"filter":"mipmap","wrap":"repeat","vflip":"true","srgb":"false","internal":"byte"},"published":1}],"outputs":[{"id":"4dfGRr","channel":0}],"code":"void mainImage( out vec4 fragColor, in vec2 fragCoord )\n{\n    // Normalized pixel coordinates (from 0 to 1)\n    vec2 uv = fragCoord/iResolution.xy;\n\tuv-=0.5;\n    float t = 0.5*iTime;\n    uv.x *= iResolution.x/iResolution.y;\n    // Time varying pixel color\n    vec4 c,col;\n    col = vec4 (0.);\n    uv.y-=0.2;\n    float m = 0.;\n    float ny=uv.y;\n    for (float i=1.0; i>=0.0;i-=0.002){\n        m-=1.;\n    \tc = texture(iChannel0, (vec2(uv.x+0.*t,-1.0*i+0.4*t))/vec2(30.0,20.0))*0.5+texture(iChannel0, (vec2(uv.x+0.1*t,-1.0*i+0.4*t))/vec2(20.0,10.0))*0.25+texture(iChannel0, (vec2(uv.x+0.02*t,-1.0*i+0.4*t))/vec2(10.0,5.0))*0.15+texture(iChannel0, (vec2(uv.x+0.08*t,-1.0*i+0.4*t))/vec2(5.0,2.0))*0.1+texture(iChannel0, (vec2(uv.x+0.07*t,-1.0*i+0.4*t))/vec2(3.0,1.0))*0.05+texture(iChannel0, (vec2(uv.x-0.2*t,-1.0*i+0.4*t))/vec2(1.0,0.5))*0.03;\n        col =(1.6-3.0*c+vec4(-0.0,-0.4,0.0,1.0));\n        \n    \tif (c.x>0.005*m-1.*uv.y+0.90){ col*=(1.0-0.5*i);break; }\n        //uv.y+=ny;\n    \t//if (c.x>40.5*i*uv.y+0.94+20.9*i){ col +=mix(col,(0.4-c)*(0.8-i),1.); }\n\n    }\n\t\n    // Output to screen\n    fragColor = col;\n}","name":"Image","description":"","type":"image"}]}