{"ver":"0.1","info":{"id":"wlVXD3","date":"1583768159","viewed":80,"name":"Evgen Kovalenko composition","username":"JoHailrake","description":"ek","likes":0,"published":1,"flags":0,"usePreview":0,"tags":["composition"],"hasliked":0,"parentid":"","parentname":""},"renderpass":[{"inputs":[],"outputs":[{"id":"4dfGRr","channel":0}],"code":"float Circle(vec2 uv, vec2 p, float r, float blur) {\nfloat d = length(uv-p);\nfloat c = smoothstep(r, r-blur, d);\nreturn c;\n}\nfloat Band (float t, float start, float end, float blur) {\nfloat step1 = smoothstep(start-blur, start+blur, t);\nfloat step2 = smoothstep(end+blur, end-blur, t);\nreturn step1*step2;\n}\nfloat Rect (vec2 uv, float left, float right, float bottom, float top, float blur) {\nfloat band1 = Band(uv.x, left, right, blur);\nfloat band2 = Band(uv.y, bottom, top, blur);\nreturn band1*band2;\n}\n\nvoid mainImage(out vec4 fragColor, in vec2 fragCoord)\n{\nvec2 uv = fragCoord.xy / iResolution.xy; // 0 <> 1.\nuv -= .5; // -0.5 <> 0.5\nuv.x *= iResolution.x/iResolution.y;\nvec3 col = vec3(0.);;\nfloat mask = 0.;\nmask = Rect(uv, -0.4, 0.435, -.4, .4, .0001);\nif(mask != Rect(uv, -0.4, 0.0, .25, .35, .0001) && mask != Rect(uv, -0.4, -0.29, .0255, .25, .0001) &&\n  mask != Rect(uv, -0.4, 0.0, -.075, .025, .0001) && mask != Rect(uv, -0.4, -0.29, -.275, -.075, .0001) &&\n  mask != Rect(uv, -0.4, 0.0, -.38, -.275, .0001) && mask != Rect(uv, 0.1, 0.21, -0.38, 0.35, 0.0001) &&\n  mask !=  Circle(uv, vec2(0.62, 0.0), 0.42, 0.0001) \n ){\n\tmask = .0; \n}\nif(mask == Circle(uv, vec2(0.72, 0.0), 0.532, 0.1)){\n\tmask = .0; \n}        \ncol = vec3(1., 0.6, 1.)*mask;\nfragColor = vec4(col, 1.0);\n}","name":"Image","description":"","type":"image"}]}