{"ver":"0.1","info":{"id":"WlVyR1","date":"1610476293","viewed":58,"name":"Simple Palm Tree With Maths","username":"spenceryonce","description":" basic palm tree using solely maths. This shader was based on IQ's Sunset shader. He is awesome. ","likes":1,"published":1,"flags":0,"usePreview":0,"tags":["basic","math","tree","palm"],"hasliked":0,"parentid":"","parentname":""},"renderpass":[{"inputs":[],"outputs":[{"id":"4dfGRr","channel":0}],"code":"void mainImage( out vec4 fragColor, in vec2 fragCoord )\n{\n    // Normalized pixel coordinates (from 0 to 1)\n    vec2 p = fragCoord/iResolution.xy;\n    vec2 q = p - vec2(0.3,0.7);\n    \n    \n    vec3 col = mix(vec3(1, 0.4, 0.1), vec3(1.0,0.8,0.3), sqrt(p.y) );\n    \n    //canopy for palm tree\n    float r = 0.2 + 0.1*cos( atan(q.y,q.x)*10.0 + 20.0*q.x + 1.0);\n    col *= smoothstep (r,r+0.01, length( q ) );\n    \n    //trunk for palm tree\n    r=0.015;\n    r += 0.002*cos(120.0*q.y);\n    r += exp(-45.0*p.y);\n    col *= 1.0 - (1.0-smoothstep (r,r+0.002, abs(q.x-0.25*sin(2.0*q.y)) ))*(1.0-smoothstep(0.0,0.1,q.y));\n\n    //output to screen\n    fragColor = vec4(col,1.0);\n}","name":"Image","description":"","type":"image"}]}