{"ver":"0.1","info":{"id":"wlXXRS","date":"1563333727","viewed":625,"name":"Psy dimension","username":"avin","description":"some visual experiment","likes":7,"published":3,"flags":0,"usePreview":0,"tags":["radials"],"hasliked":0,"parentid":"","parentname":""},"renderpass":[{"inputs":[],"outputs":[{"id":"4dfGRr","channel":0}],"code":"#define BLACK_COL vec3(24,32,38)/255.\n#define WHITE_COL vec3(245,248,250)/255.\n\nvoid mainImage( out vec4 fragColor, in vec2 fragCoord )\n{\n    vec2 uv = (fragCoord.xy - iResolution.xy * 0.5) / iResolution.y;\n\n    vec2 st = vec2(atan(uv.x, uv.y), length(uv));\n        \n    st.x += iTime*.1 + floor(st.y * 3. + iTime*.2)*0.3925;\n    \n    float g = st.x * 3.82 * 2.;\n    float b1 = fract(g);\n    float b2 = sin(st.y*50. - iTime * 10.) * .25 + .5;\n    \n    float gf = floor(mod(g, 2.)) * .6;\n    float m = step(.125 - st.y*.25 * gf, abs(b2 - b1) );        \n    \n    m = (1.-m) * abs(1. - gf + .1);  \n    \n    vec3 col = mix(BLACK_COL, WHITE_COL, m);\n\n    fragColor = vec4(col, 1.0);\n}","name":"Image","description":"","type":"image"}]}