{"ver":"0.1","info":{"id":"Ws3cWj","date":"1601680105","viewed":744,"name":"Background Removal","username":"oneshade","description":"This removes green from the picture and replaces it with a color from the background. If you want to try it on webcam make sure your in front of something green and that your not wearing green either.","likes":4,"published":3,"flags":0,"usePreview":0,"tags":["transparent","background","removal"],"hasliked":0,"parentid":"","parentname":""},"renderpass":[{"inputs":[{"id":"4dfGRn","filepath":"/media/a/8de3a3924cb95bd0e95a443fff0326c869f9d4979cd1d5b6e94e2a01f5be53e9.jpg","previewfilepath":"/media/ap/8de3a3924cb95bd0e95a443fff0326c869f9d4979cd1d5b6e94e2a01f5be53e9.jpg","type":"texture","channel":0,"sampler":{"filter":"mipmap","wrap":"repeat","vflip":"true","srgb":"false","internal":"byte"},"published":1},{"id":"XdfGRr","filepath":"/media/a/35c87bcb8d7af24c54d41122dadb619dd920646a0bd0e477e7bdc6d12876df17.webm","previewfilepath":"/media/ap/35c87bcb8d7af24c54d41122dadb619dd920646a0bd0e477e7bdc6d12876df17.webm","type":"video","channel":1,"sampler":{"filter":"linear","wrap":"clamp","vflip":"true","srgb":"false","internal":"byte"},"published":1}],"outputs":[{"id":"4dfGRr","channel":0}],"code":"bool isgreen(in vec3 color) {\n    return 0.6 * color.g > color.r && 0.6 * color.g > color.b;\n}\n\nvoid mainImage(out vec4 fragColor, in vec2 fragCoord) {\n    vec2 uv = fragCoord / iResolution.xy;\n    vec3 foreground = texture(iChannel1, uv).rgb;\n    vec3 background = texture(iChannel0, uv).rgb;\n    vec3 color = background;\n    if (!isgreen(foreground)) {\n        color = foreground;\n    }\n    fragColor = vec4(color, 1.0);\n}","name":"Image","description":"","type":"image"}]}