{"ver":"0.1","info":{"id":"X3lcRB","date":"1729519622","viewed":25,"name":"trippy 2d patterns culegamer","username":"CuleGamer","description":"strange\nmove mouse","likes":0,"published":1,"flags":0,"usePreview":0,"tags":["2d","fractal"],"hasliked":0,"parentid":"","parentname":""},"renderpass":[{"inputs":[],"outputs":[{"id":"4dfGRr","channel":0}],"code":"void mainImage(out vec4 O, in vec2 I)\n{\n    vec2 uv = (2. * I - iResolution.xy) / iResolution.y;\n    vec2 uvMouse = (2. * iMouse.xy - iResolution.xy) / iResolution.y;\n    float theta = iTime;\n    for(uint i; i < 512u; i++)\n    {\n        uv.y += uvMouse.y;\n        theta *= uvMouse.x;\n        mat2 rot = mat2(cos(theta), -sin(theta), sin(theta), cos(theta));\n        uv = abs(fract(uv) - 0.5);\n        uv *= rot;\n    }\n    float val = 0.1 / length(uv);\n    vec3 col = vec3(val);\n    O = vec4(col,1.0);\n}","name":"Image","description":"","type":"image"}]}