{"ver":"0.1","info":{"id":"XdGyRm","date":"1521376790","viewed":258,"name":"Chromatic aberration - London","username":"SolalDR","description":"Different noise apply on each color ","likes":10,"published":1,"flags":0,"usePreview":0,"tags":["noise","texture"],"hasliked":0,"parentid":"","parentname":""},"renderpass":[{"inputs":[{"id":"4dfGRn","filepath":"/media/a/8de3a3924cb95bd0e95a443fff0326c869f9d4979cd1d5b6e94e2a01f5be53e9.jpg","previewfilepath":"/media/ap/8de3a3924cb95bd0e95a443fff0326c869f9d4979cd1d5b6e94e2a01f5be53e9.jpg","type":"texture","channel":0,"sampler":{"filter":"mipmap","wrap":"repeat","vflip":"true","srgb":"false","internal":"byte"},"published":1},{"id":"XdXGzn","filepath":"/media/a/3083c722c0c738cad0f468383167a0d246f91af2bfa373e9c5c094fb8c8413e0.png","previewfilepath":"/media/ap/3083c722c0c738cad0f468383167a0d246f91af2bfa373e9c5c094fb8c8413e0.png","type":"texture","channel":1,"sampler":{"filter":"mipmap","wrap":"repeat","vflip":"true","srgb":"false","internal":"byte"},"published":1}],"outputs":[{"id":"4dfGRr","channel":0}],"code":"void mainImage( out vec4 fragColor, in vec2 fragCoord )\n{\n    // Normalized pixel coordinates (from 0 to 1)\n    vec2 uv = fragCoord/iResolution.xy;\n\n    // Time varying pixel color\n    vec3 col = 0.5 + 0.5*cos(iTime+uv.xyx+vec3(0,2,4));\n\n    \n    vec4 noiseR = texture(iChannel1, vec2(uv.x/30., uv.y/30. + iTime/100.));\n    vec4 noiseG = texture(iChannel1, vec2(uv.x/20., uv.y/20. + iTime/90.));\n    vec4 noiseB = texture(iChannel1, vec2(uv.x/40., uv.y/40. + iTime/80.));\n    \n    vec4 imageR = texture(iChannel0, uv + noiseR.xz/10.);\n    vec4 imageG = texture(iChannel0, uv + noiseG.xz/20.);\n    vec4 imageB = texture(iChannel0, uv + noiseB.xz/15.);\n    \n    vec3 color = vec3(imageR.x, imageG.y, imageB.z);// + noise.xyz;\n    \n    // Output to screen\n    fragColor = vec4(color.xyz,1.0);\n}\n","name":"Image","description":"","type":"image"}]}