{"ver":"0.1","info":{"id":"XfBSRd","date":"1706669858","viewed":23,"name":"Fork Amber/Blue 2","username":"sonicswordcane","description":"Amber/Blue (ColorCode 3-D) Anaglyph rendering","likes":0,"published":1,"flags":0,"usePreview":0,"tags":["3d","anaglyph","colorcode3d"],"hasliked":0,"parentid":"4fBXzt","parentname":"Amber/Blue Anaglyph"},"renderpass":[{"inputs":[{"id":"XdX3Rn","filepath":"/media/a/52d2a8f514c4fd2d9866587f4d7b2a5bfa1a11a0e772077d7682deb8b3b517e5.jpg","previewfilepath":"/media/ap/52d2a8f514c4fd2d9866587f4d7b2a5bfa1a11a0e772077d7682deb8b3b517e5.jpg","type":"texture","channel":0,"sampler":{"filter":"mipmap","wrap":"repeat","vflip":"true","srgb":"false","internal":"byte"},"published":1}],"outputs":[{"id":"4dfGRr","channel":0}],"code":"void mainImage( out vec4 fragColor, in vec2 fragCoord )\n{\n    // Normalized pixel coordinates (from 0 to 1)\n    vec2 uv = fragCoord/iResolution.xy;\n\n    // Fake anaglyph\n    vec4 left = texture(iChannel0, uv - vec2(0.05, 0));\n    vec4 right = texture(iChannel0, uv + vec2(0.05, 0));\n    \n    // Just copy the right's blue channel\n    fragColor = vec4(left.r, left.g, right.b, left.a);\n}","name":"Image","description":"","type":"image"}]}