{"ver":"0.1","info":{"id":"XXXyDS","date":"1726592234","viewed":14,"name":"Purple Space Skybox","username":"shatteredjade","description":"skybox","likes":0,"published":1,"flags":0,"usePreview":0,"tags":["sky","box"],"hasliked":0,"parentid":"","parentname":""},"renderpass":[{"inputs":[{"id":"4dXGzn","filepath":"/media/a/0c7bf5fe9462d5bffbd11126e82908e39be3ce56220d900f633d58fb432e56f5.png","previewfilepath":"/media/ap/0c7bf5fe9462d5bffbd11126e82908e39be3ce56220d900f633d58fb432e56f5.png","type":"texture","channel":0,"sampler":{"filter":"mipmap","wrap":"repeat","vflip":"true","srgb":"false","internal":"byte"},"published":1}],"outputs":[{"id":"4dfGRr","channel":0}],"code":"void mainImage( out vec4 fragColor, in vec2 fragCoord )\n{\n    vec2 uv = fragCoord/iResolution.xy;uv-=0.7;\n    \n    uv.x -= sin(iTime/3.);\n    \n    float sun = length(uv);\n    sun = 0.001/smoothstep(0.,1.,sun);\n    \n    vec3 x = -abs(vec3(uv.x));\n    vec3 y = -abs(vec3(uv.y));\n    \n    vec3 xy = mix(x,y,1.1);\n    \n    vec3 col = vec3(0);\n    col += 1./vec3(1.,2.,1.);\n    \n    col += sun;\n    col += xy;\n    \n    vec3 stars = 0.01/(1.-vec3(texture(iChannel0,uv)));\n    \n    col += stars;\n    \n    fragColor = vec4(col,1.0);\n}","name":"Image","description":"","type":"image"}]}